grpc_observability/__init__.py
grpc_observability/_cyobservability.cpython-310-aarch64-linux-gnu.so
grpc_observability/_measures.py
grpc_observability/_observability.py
grpc_observability/_observability_config.py
grpc_observability/_open_census_exporter.py
grpc_observability/_open_telemetry_measures.py
grpc_observability/_open_telemetry_observability.py
grpc_observability/_open_telemetry_plugin.py
grpc_observability/_views.py
grpcio_observability-1.76.0.dist-info/LICENSE
grpcio_observability-1.76.0.dist-info/METADATA
grpcio_observability-1.76.0.dist-info/WHEEL
grpcio_observability-1.76.0.dist-info/top_level.txt
grpcio_observability-1.76.0.dist-info/RECORD
