Metadata-Version: 2.1
Name: grpcio-observability
Version: 1.76.0
Summary: gRPC Python observability package
Home-page: https://grpc.io
Author: The gRPC Authors
Author-email: grpc-io@googlegroups.com
License: Apache License 2.0
Project-URL: Source Code, https://github.com/grpc/grpc/tree/master/src/python/grpcio_observability
Project-URL: Bug Tracker, https://github.com/grpc/grpc/issues
Classifier: Development Status :: 5 - Production/Stable
Classifier: Programming Language :: Python
Classifier: Programming Language :: Python :: 3
Classifier: License :: OSI Approved :: Apache Software License
Requires-Python: >=3.9
License-File: LICENSE
Requires-Dist: grpcio ==1.76.0
Requires-Dist: setuptools >=59.6.0
Requires-Dist: opentelemetry-api >=1.21.0
